<?xml version="1.0" encoding="UTF-8"?>
<!DOCTYPE plist PUBLIC "-//Apple//DTD PLIST 1.0//EN" "http://www.apple.com/DTDs/PropertyList-1.0.dtd"/>

<plist version="1.0">
    <dict>
        <key>ROOT</key>
        <array>
            <dict>
                <key>id</key>
                <string>99</string>
                <key>Event Observer</key>
                <dict>
                    <key>connectedModelId</key>
                    <string>1614</string>
                    <key>attributeName</key>
                    <string>Load</string>
                    <key>isAction</key>
                    <string>true</string>
                </dict>
                <key>Navigation Button</key>
                <dict>
                    <key>connectedModelId</key>
                    <string>1599</string>
                    <key>attributeName</key>
                    <string>Load</string>
                    <key>isAction</key>
                    <string>true</string>
                </dict>
                <key>modelId</key>
                <string>100</string>
                <key>attributesCount</key>
                <string>5</string>
            </dict>
            <dict>
                <key>id</key>
                <string>1569</string>
                <key>Navigation Button</key>
                <dict>
                    <key>connectedModelId</key>
                    <string>99</string>
                    <key>attributeName</key>
                    <string>Load</string>
                    <key>isAction</key>
                    <string>true</string>
                </dict>
                <key>Navigation Button 2</key>
                <dict>
                    <key>connectedModelId</key>
                    <string>1628</string>
                    <key>attributeName</key>
                    <string>Load</string>
                    <key>isAction</key>
                    <string>true</string>
                </dict>
                <key>modelId</key>
                <string>1570</string>
                <key>attributesCount</key>
                <string>5</string>
            </dict>
            <dict>
                <key>id</key>
                <string>1577</string>
                <key>Navigation Button 3</key>
                <dict>
                    <key>connectedModelId</key>
                    <string>1593</string>
                    <key>attributeName</key>
                    <string>Load</string>
                    <key>isAction</key>
                    <string>true</string>
                </dict>
                <key>Navigation Button 2</key>
                <dict>
                    <key>connectedModelId</key>
                    <string>1584</string>
                    <key>attributeName</key>
                    <string>Load</string>
                    <key>isAction</key>
                    <string>true</string>
                </dict>
                <key>modelId</key>
                <string>1578</string>
                <key>attributesCount</key>
                <string>5</string>
            </dict>
            <dict>
                <key>id</key>
                <string>1584</string>
                <key>modelId</key>
                <string>1585</string>
                <key>attributesCount</key>
                <string>3</string>
            </dict>
            <dict>
                <key>id</key>
                <string>1593</string>
                <key>1</key>
                <dict>
                    <key>connectedModelId</key>
                    <string>1393</string>
                    <key>attributeName</key>
                    <string>Load</string>
                    <key>isAction</key>
                    <string>true</string>
                </dict>
                <key>2</key>
                <dict>
                    <key>connectedModelId</key>
                    <string>1628</string>
                    <key>attributeName</key>
                    <string>Load</string>
                    <key>isAction</key>
                    <string>true</string>
                </dict>
                <key>modelId</key>
                <string>1594</string>
                <key>attributesCount</key>
                <string>5</string>
            </dict>
            <dict>
                <key>id</key>
                <string>1599</string>
                <key>modelId</key>
                <string>1600</string>
                <key>attributesCount</key>
                <string>3</string>
            </dict>
            <dict>
                <key>id</key>
                <string>1614</string>
                <key>modelId</key>
                <string>1615</string>
                <key>attributesCount</key>
                <string>3</string>
            </dict>
            <dict>
                <key>id</key>
                <string>1648</string>
                <key>Navigation Button</key>
                <dict>
                    <key>connectedModelId</key>
                    <string>1577</string>
                    <key>attributeName</key>
                    <string>Load</string>
                    <key>isAction</key>
                    <string>true</string>
                </dict>
                <key>modelId</key>
                <string>1649</string>
                <key>attributesCount</key>
                <string>4</string>
            </dict>
            <dict>
                <key>id</key>
                <string>13834</string>
                <key>Navigation Button</key>
                <dict>
                    <key>connectedModelId</key>
                    <string>14057</string>
                    <key>attributeName</key>
                    <string>Load</string>
                    <key>isAction</key>
                    <string>true</string>
                </dict>
                <key>modelId</key>
                <string>13835</string>
                <key>attributesCount</key>
                <string>4</string>
            </dict>
            <dict>
                <key>id</key>
                <string>14057</string>
                <key>Navigation Button</key>
                <dict>
                    <key>connectedModelId</key>
                    <string>1577</string>
                    <key>attributeName</key>
                    <string>Load</string>
                    <key>isAction</key>
                    <string>true</string>
                </dict>
                <key>modelId</key>
                <string>14058</string>
                <key>attributesCount</key>
                <string>4</string>
            </dict>
            <dict>
                <key>id</key>
                <string>16851</string>
                <key>Navigation Button</key>
                <dict>
                    <key>connectedModelId</key>
                    <string>16863</string>
                    <key>attributeName</key>
                    <string>Load</string>
                    <key>isAction</key>
                    <string>true</string>
                </dict>
                <key>modelId</key>
                <string>16852</string>
                <key>attributesCount</key>
                <string>4</string>
            </dict>
            <dict>
                <key>id</key>
                <string>16863</string>
                <key>Navigation Button</key>
                <dict>
                    <key>connectedModelId</key>
                    <string>16908</string>
                    <key>attributeName</key>
                    <string>Load</string>
                    <key>isAction</key>
                    <string>true</string>
                </dict>
                <key>modelId</key>
                <string>16864</string>
                <key>attributesCount</key>
                <string>4</string>
            </dict>
            <dict>
                <key>id</key>
                <string>16908</string>
                <key>Navigation Button</key>
                <dict>
                    <key>connectedModelId</key>
                    <string>1648</string>
                    <key>attributeName</key>
                    <string>Load</string>
                    <key>isAction</key>
                    <string>true</string>
                </dict>
                <key>modelId</key>
                <string>16909</string>
                <key>attributesCount</key>
                <string>4</string>
            </dict>
        </array>
    </dict>
</plist>
